<?xml version="1.0" encoding="utf-8" ?><dwsync><file name="accordion.js" server="canonicaleye.org///" local="3750379200" remote="3750379200" Dst="-1" /><file name="accordion.min.js" server="canonicaleye.org///" local="3763190520" remote="3763190520" Dst="-1" /><file name="autocomplete.js" server="canonicaleye.org///" local="3750379200" remote="3750379200" Dst="-1" /><file name="autocomplete.min.js" server="canonicaleye.org///" local="3763190520" remote="3763190520" Dst="-1" /><file name="button.js" server="canonicaleye.org///" local="3750379200" remote="3750379200" Dst="-1" /><file name="button.min.js" server="canonicaleye.org///" local="3763190520" remote="3763190520" Dst="-1" /><file name="checkboxradio.js" server="canonicaleye.org///" local="3750379200" remote="3750379200" Dst="-1" /><file name="checkboxradio.min.js" server="canonicaleye.org///" local="3750379200" remote="3750379200" Dst="-1" /><file name="controlgroup.js" server="canonicaleye.org///" local="3750379200" remote="3750379200" Dst="-1" /><file name="controlgroup.min.js" server="canonicaleye.org///" local="3750379200" remote="3750379200" Dst="-1" /><file name="core.js" server="canonicaleye.org///" local="3750379200" remote="3750379200" Dst="-1" /><file name="core.min.js" server="canonicaleye.org///" local="3763190520" remote="3763190520" Dst="-1" /><file name="datepicker.js" server="canonicaleye.org///" local="3750379200" remote="3750379200" Dst="-1" /><file name="datepicker.min.js" server="canonicaleye.org///" local="3763190520" remote="3763190520" Dst="-1" /><file name="dialog.js" server="canonicaleye.org///" local="3750379200" remote="3750379200" Dst="-1" /><file name="dialog.min.js" server="canonicaleye.org///" local="3763190520" remote="3763190520" Dst="-1" /><file name="draggable.js" server="canonicaleye.org///" local="3750379200" remote="3750379200" Dst="-1" /><file name="draggable.min.js" server="canonicaleye.org///" local="3763190520" remote="3763190520" Dst="-1" /><file name="droppable.js" server="canonicaleye.org///" local="3750379200" remote="3750379200" Dst="-1" /><file name="droppable.min.js" server="canonicaleye.org///" local="3763190520" remote="3763190520" Dst="-1" /><file name="effect-blind.js" server="canonicaleye.org///" local="3750379200" remote="3750379200" Dst="-1" /><file name="effect-blind.min.js" server="canonicaleye.org///" local="3750379200" remote="3750379200" Dst="-1" /><file name="effect-bounce.js" server="canonicaleye.org///" local="3750379200" remote="3750379200" Dst="-1" /><file name="effect-bounce.min.js" server="canonicaleye.org///" local="3750379200" remote="3750379200" Dst="-1" /><file name="effect-clip.js" server="canonicaleye.org///" local="3750379200" remote="3750379200" Dst="-1" /><file name="effect-clip.min.js" server="canonicaleye.org///" local="3750379200" remote="3750379200" Dst="-1" /><file name="effect-drop.js" server="canonicaleye.org///" local="3750379200" remote="3750379200" Dst="-1" /><file name="effect-drop.min.js" server="canonicaleye.org///" local="3750379200" remote="3750379200" Dst="-1" /><file name="effect-explode.js" server="canonicaleye.org///" local="3750379200" remote="3750379200" Dst="-1" /><file name="effect-explode.min.js" server="canonicaleye.org///" local="3750379200" remote="3750379200" Dst="-1" /><file name="effect-fade.js" server="canonicaleye.org///" local="3750379200" remote="3750379200" Dst="-1" /><file name="effect-fade.min.js" server="canonicaleye.org///" local="3750379200" remote="3750379200" Dst="-1" /><file name="effect-fold.js" server="canonicaleye.org///" local="3750379200" remote="3750379200" Dst="-1" /><file name="effect-fold.min.js" server="canonicaleye.org///" local="3750379200" remote="3750379200" Dst="-1" /><file name="effect-highlight.js" server="canonicaleye.org///" local="3750379200" remote="3750379200" Dst="-1" /><file name="effect-highlight.min.js" server="canonicaleye.org///" local="3750379200" remote="3750379200" Dst="-1" /><file name="effect-puff.js" server="canonicaleye.org///" local="3750379200" remote="3750379200" Dst="-1" /><file name="effect-puff.min.js" server="canonicaleye.org///" local="3750379200" remote="3750379200" Dst="-1" /><file name="effect-pulsate.js" server="canonicaleye.org///" local="3750379200" remote="3750379200" Dst="-1" /><file name="effect-pulsate.min.js" server="canonicaleye.org///" local="3750379200" remote="3750379200" Dst="-1" /><file name="effect-scale.js" server="canonicaleye.org///" local="3750379200" remote="3750379200" Dst="-1" /><file name="effect-scale.min.js" server="canonicaleye.org///" local="3750379200" remote="3750379200" Dst="-1" /><file name="effect-shake.js" server="canonicaleye.org///" local="3750379200" remote="3750379200" Dst="-1" /><file name="effect-shake.min.js" server="canonicaleye.org///" local="3750379200" remote="3750379200" Dst="-1" /><file name="effect-size.js" server="canonicaleye.org///" local="3750379200" remote="3750379200" Dst="-1" /><file name="effect-size.min.js" server="canonicaleye.org///" local="3750379200" remote="3750379200" Dst="-1" /><file name="effect-slide.js" server="canonicaleye.org///" local="3750379200" remote="3750379200" Dst="-1" /><file name="effect-slide.min.js" server="canonicaleye.org///" local="3750379200" remote="3750379200" Dst="-1" /><file name="effect-transfer.js" server="canonicaleye.org///" local="3750379200" remote="3750379200" Dst="-1" /><file name="effect-transfer.min.js" server="canonicaleye.org///" local="3750379200" remote="3750379200" Dst="-1" /><file name="effect.js" server="canonicaleye.org///" local="3750379200" remote="3750379200" Dst="-1" /><file name="effect.min.js" server="canonicaleye.org///" local="3763190520" remote="3763190520" Dst="-1" /><file name="menu.js" server="canonicaleye.org///" local="3750379200" remote="3750379200" Dst="-1" /><file name="menu.min.js" server="canonicaleye.org///" local="3763190520" remote="3763190520" Dst="-1" /><file name="mouse.js" server="canonicaleye.org///" local="3750379200" remote="3750379200" Dst="-1" /><file name="mouse.min.js" server="canonicaleye.org///" local="3750379200" remote="3750379200" Dst="-1" /><file name="progressbar.js" server="canonicaleye.org///" local="3750379200" remote="3750379200" Dst="-1" /><file name="progressbar.min.js" server="canonicaleye.org///" local="3750379200" remote="3750379200" Dst="-1" /><file name="resizable.js" server="canonicaleye.org///" local="3750379200" remote="3750379200" Dst="-1" /><file name="resizable.min.js" server="canonicaleye.org///" local="3763190520" remote="3763190520" Dst="-1" /><file name="selectable.js" server="canonicaleye.org///" local="3750379200" remote="3750379200" Dst="-1" /><file name="selectable.min.js" server="canonicaleye.org///" local="3750379200" remote="3750379200" Dst="-1" /><file name="selectmenu.js" server="canonicaleye.org///" local="3750379200" remote="3750379200" Dst="-1" /><file name="selectmenu.min.js" server="canonicaleye.org///" local="3750379200" remote="3750379200" Dst="-1" /><file name="slider.js" server="canonicaleye.org///" local="3750379200" remote="3750379200" Dst="-1" /><file name="slider.min.js" server="canonicaleye.org///" local="3763190520" remote="3763190520" Dst="-1" /><file name="sortable.js" server="canonicaleye.org///" local="3750379200" remote="3750379200" Dst="-1" /><file name="sortable.min.js" server="canonicaleye.org///" local="3763190520" remote="3763190520" Dst="-1" /><file name="spinner.js" server="canonicaleye.org///" local="3750379200" remote="3750379200" Dst="-1" /><file name="spinner.min.js" server="canonicaleye.org///" local="3750379200" remote="3750379200" Dst="-1" /><file name="tabs.js" server="canonicaleye.org///" local="3750379200" remote="3750379200" Dst="-1" /><file name="tabs.min.js" server="canonicaleye.org///" local="3750379200" remote="3750379200" Dst="-1" /><file name="tooltip.js" server="canonicaleye.org///" local="3750379200" remote="3750379200" Dst="-1" /><file name="tooltip.min.js" server="canonicaleye.org///" local="3763190520" remote="3763190520" Dst="-1" /></dwsync>